[{"id":0,"href":"/docs/","title":"オンライン自習室","section":"オンライン自習室","content":" オンライン自習室 勉強は「才能」じゃなく\n仕組みで勝てる ここは受験の勉強法を、迷わず実行できる形にまとめる場所。\n「がんばる」より先に、毎日回る型を作ろう。 \u0026lt;div class=\u0026quot;ui-home-actions\u0026quot;\u0026gt; \u0026lt;a class=\u0026quot;btn primary\u0026quot; href=\u0026quot;/docs/01_design/01_blueprint/\u0026quot;\u0026gt;最優先：全体設計へ\u0026lt;/a\u0026gt; \u0026lt;a class=\u0026quot;btn ghost\u0026quot; href=\u0026quot;/docs/05_routine/01_daily60/\u0026quot;\u0026gt;毎日の型（ルーティン）へ\u0026lt;/a\u0026gt; \u0026lt;a class=\u0026quot;btn ghost\u0026quot; href=\u0026quot;/docs/04_mistakes/01_miss_types/\u0026quot;\u0026gt;ミス分析と対策へ\u0026lt;/a\u0026gt; \u0026lt;/div\u0026gt; \u0026lt;div class=\u0026quot;ui-home-metrics\u0026quot;\u0026gt; \u0026lt;div class=\u0026quot;m\u0026quot;\u0026gt; \u0026lt;div class=\u0026quot;k\u0026quot;\u0026gt;優先度\u0026lt;/div\u0026gt; \u0026lt;div class=\u0026quot;v\u0026quot;\u0026gt;全体設計 → 毎日の型\u0026lt;/div\u0026gt; \u0026lt;/div\u0026gt; \u0026lt;div class=\u0026quot;m\u0026quot;\u0026gt; \u0026lt;div class=\u0026quot;k\u0026quot;\u0026gt;主役\u0026lt;/div\u0026gt; \u0026lt;div class=\u0026quot;v\u0026quot;\u0026gt;ミス修正（再発防止）\u0026lt;/div\u0026gt; \u0026lt;/div\u0026gt; \u0026lt;div class=\u0026quot;m\u0026quot;\u0026gt; \u0026lt;div class=\u0026quot;k\u0026quot;\u0026gt;基本\u0026lt;/div\u0026gt; \u0026lt;div class=\u0026quot;v\u0026quot;\u0026gt;スマホ前提で回す\u0026lt;/div\u0026gt; \u0026lt;/div\u0026gt; \u0026lt;/div\u0026gt; 目的別：今すぐ選ぶ 「困ってること」から入れば迷いが消える。まずは1つだけでOK。 \u0026lt;div class=\u0026quot;ui-home-pills\u0026quot;\u0026gt; \u0026lt;a class=\u0026quot;pill\u0026quot; href=\u0026quot;/docs/01_design/01_blueprint/\u0026quot;\u0026gt;全体がぐちゃぐちゃ\u0026lt;/a\u0026gt; \u0026lt;a class=\u0026quot;pill\u0026quot; href=\u0026quot;/docs/05_routine/01_daily60/\u0026quot;\u0026gt;毎日続かない\u0026lt;/a\u0026gt; \u0026lt;a class=\u0026quot;pill\u0026quot; href=\u0026quot;/docs/04_mistakes/01_miss_types/\u0026quot;\u0026gt;伸びない原因が不明\u0026lt;/a\u0026gt; \u0026lt;a class=\u0026quot;pill\u0026quot; href=\u0026quot;/docs/02_memory/01_recall/\u0026quot;\u0026gt;暗記がつらい\u0026lt;/a\u0026gt; \u0026lt;a class=\u0026quot;pill\u0026quot; href=\u0026quot;/docs/03_review/01_review_flow/\u0026quot;\u0026gt;復習が回らない\u0026lt;/a\u0026gt; \u0026lt;/div\u0026gt; まず読むべき3本（最短で効く順） 順番どおりに読むと、あなたの勉強が“回り始める”。 \u0026lt;div class=\u0026quot;ui-home-cards\u0026quot;\u0026gt; \u0026lt;a class=\u0026quot;card\u0026quot; href=\u0026quot;/docs/01_design/01_blueprint/\u0026quot;\u0026gt; \u0026lt;div class=\u0026quot;top\u0026quot;\u0026gt; \u0026lt;div class=\u0026quot;icon\u0026quot;\u0026gt;①\u0026lt;/div\u0026gt; \u0026lt;div class=\u0026quot;ttl\u0026quot;\u0026gt;全体設計（やること/捨てること）\u0026lt;/div\u0026gt; \u0026lt;/div\u0026gt; \u0026lt;div class=\u0026quot;desc\u0026quot;\u0026gt; 伸びない人は「努力不足」より\u0026lt;strong\u0026gt;優先順位が崩れてる\u0026lt;/strong\u0026gt;ことが多い。 まずは科目・単元・時間配分を“設計”して、迷いを消す。 \u0026lt;/div\u0026gt; \u0026lt;div class=\u0026quot;meta\u0026quot;\u0026gt;読む → 迷いが消えて、勉強が軽くなる\u0026lt;/div\u0026gt; \u0026lt;/a\u0026gt; \u0026lt;a class=\u0026quot;card\u0026quot; href=\u0026quot;/docs/05_routine/01_daily60/\u0026quot;\u0026gt; \u0026lt;div class=\u0026quot;top\u0026quot;\u0026gt; \u0026lt;div class=\u0026quot;icon\u0026quot;\u0026gt;②\u0026lt;/div\u0026gt; \u0026lt;div class=\u0026quot;ttl\u0026quot;\u0026gt;毎日の型（60分/120分/週末）\u0026lt;/div\u0026gt; \u0026lt;/div\u0026gt; \u0026lt;div class=\u0026quot;desc\u0026quot;\u0026gt; 勉強が続かない原因は、やる気じゃなく\u0026lt;strong\u0026gt;判断コスト\u0026lt;/strong\u0026gt;。 “毎日やる順番”を固定して、実行を自動化する。 \u0026lt;/div\u0026gt; \u0026lt;div class=\u0026quot;meta\u0026quot;\u0026gt;読む → 継続が安定して、ミスが溜まらない\u0026lt;/div\u0026gt; \u0026lt;/a\u0026gt; \u0026lt;a class=\u0026quot;card\u0026quot; href=\u0026quot;/docs/04_mistakes/01_miss_types/\u0026quot;\u0026gt; \u0026lt;div class=\u0026quot;top\u0026quot;\u0026gt; \u0026lt;div class=\u0026quot;icon\u0026quot;\u0026gt;③\u0026lt;/div\u0026gt; \u0026lt;div class=\u0026quot;ttl\u0026quot;\u0026gt;ミスの5分類と対策（再発防止が主役）\u0026lt;/div\u0026gt; \u0026lt;/div\u0026gt; \u0026lt;div class=\u0026quot;desc\u0026quot;\u0026gt; 問題を解く目的は“量をこなす”じゃない。\u0026lt;strong\u0026gt;ミス発見\u0026lt;/strong\u0026gt;のため。 原因を分類できるほど、修正が速くなる。 \u0026lt;/div\u0026gt; \u0026lt;div class=\u0026quot;meta\u0026quot;\u0026gt;読む → 同じミスが減って、点が伸びる\u0026lt;/div\u0026gt; \u0026lt;/a\u0026gt; \u0026lt;/div\u0026gt; このサイトのルール（最重要） 問題は主役“っぽく見える”が、本当の主役は「再発防止」（ミスを潰した数が伸びを決める） 分類は1つじゃない（強化段階・理解度・教科でやり方を変える） 時間の訓練は、普段の勉強でやりすぎない（必要な時期に“過去問実習”で固める） ※学校の成績の取り方とは切り分けて設計（受験向け）。 次に伸ばす領域（順番） あなたの状態に合わせて、読む順番を変えていい。迷うなら上から。 \u0026lt;div class=\u0026quot;ui-home-cards\u0026quot;\u0026gt; \u0026lt;a class=\u0026quot;card\u0026quot; href=\u0026quot;/docs/02_memory/01_recall/\u0026quot;\u0026gt; \u0026lt;div class=\u0026quot;top\u0026quot;\u0026gt; \u0026lt;div class=\u0026quot;icon\u0026quot;\u0026gt;記\u0026lt;/div\u0026gt; \u0026lt;div class=\u0026quot;ttl\u0026quot;\u0026gt;暗記のやり方\u0026lt;/div\u0026gt; \u0026lt;/div\u0026gt; \u0026lt;div class=\u0026quot;desc\u0026quot;\u0026gt;暗記は“読む”より\u0026lt;strong\u0026gt;思い出す訓練\u0026lt;/strong\u0026gt;。回し方と負荷調整がすべて。\u0026lt;/div\u0026gt; \u0026lt;div class=\u0026quot;meta\u0026quot;\u0026gt;読みどころ → 忘却を前提に設計する\u0026lt;/div\u0026gt; \u0026lt;/a\u0026gt; \u0026lt;a class=\u0026quot;card\u0026quot; href=\u0026quot;/docs/03_review/01_review_flow/\u0026quot;\u0026gt; \u0026lt;div class=\u0026quot;top\u0026quot;\u0026gt; \u0026lt;div class=\u0026quot;icon\u0026quot;\u0026gt;復\u0026lt;/div\u0026gt; \u0026lt;div class=\u0026quot;ttl\u0026quot;\u0026gt;復習のやり方\u0026lt;/div\u0026gt; \u0026lt;/div\u0026gt; \u0026lt;div class=\u0026quot;desc\u0026quot;\u0026gt;復習は“時間をかける”ほど良いわけじゃない。\u0026lt;strong\u0026gt;再発防止の最短手順\u0026lt;/strong\u0026gt;を固定する。\u0026lt;/div\u0026gt; \u0026lt;div class=\u0026quot;meta\u0026quot;\u0026gt;読みどころ → ルーティンに埋め込む\u0026lt;/div\u0026gt; \u0026lt;/a\u0026gt; \u0026lt;a class=\u0026quot;card\u0026quot; href=\u0026quot;/docs/04_mistakes/01_miss_types/\u0026quot;\u0026gt; \u0026lt;div class=\u0026quot;top\u0026quot;\u0026gt; \u0026lt;div class=\u0026quot;icon\u0026quot;\u0026gt;ミ\u0026lt;/div\u0026gt; \u0026lt;div class=\u0026quot;ttl\u0026quot;\u0026gt;ミス分析と対策\u0026lt;/div\u0026gt; \u0026lt;/div\u0026gt; \u0026lt;div class=\u0026quot;desc\u0026quot;\u0026gt;ミスの種類が分かれば、修正は“テンプレ化”できる。伸びる人はここが速い。\u0026lt;/div\u0026gt; \u0026lt;div class=\u0026quot;meta\u0026quot;\u0026gt;読みどころ → 原因ラベルを固定する\u0026lt;/div\u0026gt; \u0026lt;/a\u0026gt; \u0026lt;/div\u0026gt; "},{"id":1,"href":"/docs/04_mistakes/01_miss_types/","title":"ミスの5分類と対策（完成版：理屈＋手順＋チェック）","section":"ミス分析と対策","content":" 完成版 ミスは「気合い」で減らない。分類すると減る ミスの正体は“原因の種類が違う”こと。種類が違えば、対策も変わる。だから分類が最短。 結論（ミス対策の最短） ミスは5分類で十分。\n1)知識不足 2)理解不足 3)手順ミス 4)条件読み違い 5)ケアレス。\nそれぞれ直し方の“型”が違う。型を固定すると再発が落ちる。\nなぜ「分類」が最強なのか（理屈）#\rミスが減らない人は、だいたいこうしてる：\n間違えた → 解説を読む → 「分かった」 → 次も同じところで落ちる 間違えた → 「気をつける」 → 次も落ちる 理由はシンプルで、“原因”が特定されてないから。\n原因が特定されてないと、対策が毎回ブレる。ブレると再現できない。\n逆に、原因がラベルで固定されると――\n対策が毎回同じになる 勉強時間が短くなる（迷わない） 再発が減る（型が働く） ミス5分類（これで確定）#\r① 知識不足 覚えてない／知らない 暗記の問題。再生（テスト）でしか直らない。 ② 理解不足 理由が弱い／仕組みが曖昧 説明ができない、なぜそうなるかが言えない。 ③ 手順ミス 解き方の順序が固定されてない 問題を見るたびにやり方が変わる、途中で迷う。 ④ 条件読み違い 問題文の処理が雑 条件を落とす、聞かれてることがズレる。 ⑤ ケアレス 転記・符号・単位・計算ミス 注意力じゃなく、チェック手順の問題。 ① 知識不足：直し方の型#\rなぜこれで直る？#\r知識不足は「理解」ではなく「記憶」なので、読むだけだと残りにくい。\n見ずに言える（解ける）状態を作る必要がある。\n手順（最短）#\r再生テスト：隠して言う／小テスト形式 間違いだけチェックをつける 翌日にチェックだけ再テスト（最重要） ② 理解不足：直し方の型#\rなぜこれで直る？#\r理解不足は「情報のつながり」が弱い状態。\nポイントは理由を1文にすること。長文は続かないし、運用できない。\n手順（最短）#\r理由を1文：教科書や解説から「理由の核」だけ抜く 例を1つ：典型パターンを1つだけ添える（図でもOK） すぐ判定：同類題を1問解く（読むだけで終わらない） ③ 手順ミス：直し方の型#\rなぜこれで直る？#\r理解できてても、本番で崩れるのは順序が固定されてないから。\n受験の安定は「型」で作る。型＝毎回同じ順番。\n手順（最短）#\r解き方を3手：①まず何を見る ②次に何をする ③最後に何を確認 チェック1つ：失敗しがちな箇所を“最後に確認”に組み込む 再テスト：同類題を時間を測って1問 「気をつける」は禁止 対策は必ず手順に埋め込む。「最後に○○を確認する」まで落とす。\n④ 条件読み違い：直し方の型#\rなぜこれで直る？#\r読み違いは「国語力」じゃなくて、条件処理の手順がないことが原因になりやすい。\n条件は“読む”じゃなく、処理する。\n手順（最短）#\r線引き：条件・制約・聞かれてることに線 箇条書き：条件を2〜4個に分解して書く（短く） 最後に戻る：解答前に条件に戻って照合 ⑤ ケアレス：直し方の型#\rなぜこれで直る？#\rケアレスは「集中力」より、チェック箇所が固定されていないのが原因。\nチェックは毎回同じ場所を見る“儀式”にすると強い。\n手順（最短）#\r固定チェック表：符号／単位／桁／転記／条件 最後の10秒は必ずチェック表を見る ミスが出た項目は次回から最優先で見る 「分類→対策」実例（そのまま真似してOK）#\r例：数学 ラベル：③ 手順ミス 置換した後に戻すのを忘れた。 対策（手順に埋め込む） ③の最後に「元に戻すチェック」を必ず入れる。 例：英語 ラベル：④ 条件読み違い 設問が「理由」を聞いてるのに、内容説明で答えた。 対策（処理手順） 設問の動詞（理由/要約/具体例）に線→答えの型を先に決める。 今日のチェック（YESなら再発が落ちる） ミスにラベルを貼った（5分類のどれか） 対策が「行動」になっている（気をつける禁止） 同類題を1問、見ずにやり直した 次に読む → 毎日60分ルーティン（完成版）\n→ 復習の手順（テンプレ：短く強く）\n参考（根拠として有名な整理だけ）#\r「思い出す練習」が長期保持を強める（テスト効果） 間隔を空けて復習すると残りやすい（間隔効果） 有効学習法として practice testing / distributed practice が高評価と整理されている（学習法の総説） "},{"id":2,"href":"/docs/03_review/01_review_flow/","title":"復習の手順（テンプレ：短く強く／完成版）","section":"復習のやり方","content":" 完成版 復習は「長くやる」より「次に正解する形」を作る 復習のゴールは“理解した気”じゃない。次に同じ形が出たとき、時間内に正解できること。 結論（復習はこれだけ） 復習は「原因ラベル → 直し方1行 → すぐ再テスト」の3点セット。\nこれを毎回同じ手順で回すと、復習がブレなくなる。\nなぜ「短く強く」が正しいのか（理屈）#\r復習が長くなる原因はだいたい2つ。\n“安心”のために読み続ける（理解した気になる） 何をすれば直るかが曖昧（だから時間をかけてしまう） でも受験では、点に直結するのは「再現できること」。\nつまり、復習の中心は「読む」ではなく“思い出す／解く”に寄せた方が強い。\nただ読む：本番の動作と違う（本番は見ずに解く） すぐ再テスト：本番の動作に近い（再現性が上がる） 復習が効く条件 復習が効いている状態＝「次に同じ形が出たら、何をして正解するか」が決まっている状態。\nまず整理：「理解不足」と「手順が曖昧」は別#\rここを混ぜるから、復習がグダる。\n理解不足 なぜそうなるか／理由が弱い 例：公式の意味、現象の仕組み、証明の流れが説明できない 手順が曖昧 どう解くか／順序が固定されてない 例：問題を見るたびにやり方が変わる、途中で迷う、計算の順番が毎回違う 理解できていても、手順が固定されていないと本番で崩れる。\n逆に、手順が固定されると、理解が浅くても点が伸びる場面が多い（特に典型問題）。\n復習テンプレ（これを毎回コピペ運用）#\r原因ラベル：知識／理解／手順／読み違い／ケアレス 原因1行：「なぜ落ちたか」を1行で言う（長文禁止） 直し方1行：次に同じ形なら何をするか（行動で書く） すぐ再テスト：同じ問題 or 同類題を1問、見ずに解く コツ 「原因」と「直し方」は1行。長くなるほど実行できない。\n直し方は「気をつける」禁止。手順に落とす（例：最後に条件を線引きして再確認）。\nラベル別：直し方の型（ここだけ覚えればOK）#\r1) 知識不足（覚えてない）#\r直し方：再生テスト（隠して言う／小テスト） 再テスト：翌日にもう一回（ここが大事） 2) 理解不足（理由が弱い）#\r直し方：“理由を1文”にする（教科書から拾って1文化） 再テスト：同類題を1問すぐ解く（読むだけで終わらない） 3) 手順が曖昧（解き方がブレる）#\r直し方：解き方を3手に固定（順番が命） 再テスト：同類題を時間を測って解く 4) 読み違い（条件処理が雑）#\r直し方：条件に線→条件を箇条書き→最後に条件に戻る 再テスト：同類題で「条件処理だけ丁寧に」やる 5) ケアレス（符号・転記・単位など）#\r直し方：見直し箇所を固定（毎回同じ場所を見る） 再テスト：見直しチェック込みで解き直す 具体例（実際の復習メモの形）#\r例：数学（手順ミス） 原因1行 置換したあとに「元の変数に戻す」を忘れて式が崩れた。 直し方1行 置換したら最後に「戻す」チェックを必ず入れる（解答欄の直前）。 例：英語（知識＋読み違い） 原因1行 that節を見落としてSVの区切りがズレた。 直し方1行 接続詞・関係詞を○で囲み、節のカタマリごとに線を引く。 どれくらい時間をかける？（目安）#\r復習メモ：1問あたり1〜3分 再テスト：1問（または同類題1問） それ以上やるのは、基本的に「原因が曖昧」なサイン\n→ まずラベルを決め直す スマホで読む人向け：最小チェック（今日やること）#\rYESなら今日の復習は勝ち 原因ラベルをつけた（知識/理解/手順/読み/ケアレス） 原因と直し方が“1行”で書けた 見ずに1問やり直した（ここまでが復習） 次に読む → ミスの5分類と対策（完成版）\n→ 毎日60分ルーティン（完成版）\n参考（根拠として有名なやつだけ）#\rRoediger \u0026amp; Karpicke (2006)：「テスト（思い出す練習）」が長期保持を強める（テスト効果） Dunlosky et al. (2013)：「練習テスト」「分散学習」が高い有効性として整理されている Cepeda et al. (2006)：「間隔を空ける復習（分散）」の効果を大量研究で整理（メタ分析） "},{"id":3,"href":"/docs/02_memory/01_recall/","title":"暗記は「思い出す」が9割（完成版：理屈つき）","section":"暗記と復習","content":" 完成版 暗記は「書いた量」ではなく「思い出せた回数」で決まる “勉強した感”が強い方法ほど、実は残りにくい。受験は感覚じゃなく再現性で勝つ。 結論（最短ルール） 暗記の中心は「思い出す練習」にする。\n見る→書く（作業）を長くやるより、見たら隠して言う／解くを回したほうが、長期で残る。\nなぜ「思い出す」が強いのか（理屈＋研究）#\r人間の記憶は、ただ情報を“入れる”よりも、必要なときに引き出す練習をしたほうが強くなる。\n何度も読み直すと「分かった気」になりやすい でも本番は、見ないで思い出す必要がある だから勉強の時点で「本番と同じ動作（思い出す）」を入れた方が強い この効果は研究でも繰り返し示されていて、読み直し中心より、テスト（想起）中心の方が時間が経った後に成績が上がりやすいことが報告されている（いわゆるテスト効果）。 :contentReference[oaicite:4]{index=4}\n勘違いしやすいポイント 「今すぐできる」＝「本番でもできる」ではない。\n読み直しは一時的に楽になるけど、あとで落ちやすい。逆に、思い出す練習はその場ではきついが、あとで強い。\n最短で伸びる暗記手順（テンプレ）#\r見て→隠して→言う（または解く）：まず1回「思い出す」 間違えたら：答えを見て、すぐもう一回隠して言う（修正は最小で） 翌日：同じ形式で再テスト（ここが一番効く） 3日後・7日後：まとめて再テスト（忘却前提） なぜ「翌日・3日後・7日後」なのか？\nまとめてやるより、間を空けて繰り返す方が長期で残りやすいことが多くの研究で示されている（間隔効果）。 :contentReference[oaicite:5]{index=5}\n具体例（英単語・用語・公式）#\r英単語#\r単語を見て日本語を言う（または逆） 言えなかった単語だけチェックをつける そのチェックだけをもう一周（全体をやり直さない） 理社の用語#\r用語を見て「1文で説明」 1文が出ないなら、教科書を見て1文だけ作り直す 次は教科書を閉じて同じ1文を再生 数学の公式#\r公式を写すより、「この公式を使う典型問題」を1問解く 解けなければ、公式そのものじゃなく使い所が抜けている可能性が高い よくある失敗と修正#\r失敗 ずっと書いて満足する 修正：書く前に「隠して言う」を1回入れる。書くのは最後。 失敗 全部を何周もして時間が溶ける 修正：「間違えたものだけ」を周回。正解は捨てる。 失敗 復習が気分になる 修正：翌日の再テストだけは固定。間隔を空けるほど残りやすい。 :contentReference[oaicite:6]{index=6} 失敗 「きつい＝向いてない」と思う 修正：思い出す練習は最初きついのが正常。むしろそれが効果のサイン。 今日のチェック（3つだけ） 書く前に「隠して言う／解く」を入れた 間違えたら、答えを見てすぐもう一回「隠して言う」までやった 翌日の再テストを予定に入れた 次に読む → 忘却前提の復習設計（いつ復習するか）\n→ 復習の手順テンプレ（短く強く）\n"},{"id":4,"href":"/docs/01_design/01_blueprint/","title":"最短で伸ばす“全体設計”（完成版）","section":"勉強の基本設計","content":" 完成版 受験勉強は「本番で解ける」を作る作業 やることは多い。でも順番と型を固定すれば、迷いは消える。ここだけで全体が回る。 結論（これだけ） 伸びる人は「問題 → ミス分類 → 復習」を毎日回している。理解は必要だが、理解だけでは点にならない。“正解できる状態”を作るのが勉強。\nゴール 「説明できる」ではなく「本番で解ける」 解ける状態＝同じミスをしない／時間内に処理できる／再現できる 勝ち筋 問題時間を最大化する 理解は短く、問題で判定し、ミスを潰す。これが最短。 1) 勉強の基本ループ（毎日これ）#\r問題を解く（最初から満点狙いじゃなくてOK。判定のために解く） ミスを分類（理由を“言語化”してラベルを貼る） 復習で再発防止（次回の正解率を上げる最小作業だけする） 重要：復習は“納得”じゃない 復習の目的は「分かった気」ではなく、次に同じ問題を落とさない状態を作ること。だから復習は短くていい。\n2) 優先順位（伸びる順番）#\rこれが崩れると一生迷う。\n基本はこの順番。\n頻出×取れる問題（努力が点になりやすい） ミスが多い単元（改善余地が大きい） 暗記で即伸びる範囲（英単語・古文単語・公式・用語など） 理解系の詰め（必要分だけ） 伸びない人は「好きな単元」や「気分」で順番が毎日変わる。\n3) 時間配分（迷ったらこれ）#\r平常期：理解 3：問題 7 直前期：理解 1：問題 9（演習と復習が主） 今日の判定（YESなら伸びる日） 勉強時間の半分以上を「問題」に使った 間違いをその場で1つ“潰した” 次にやる問題が決まっている 4) 暗記の原理（最短）#\r暗記は「書く量」ではなく、思い出す回数で決まる。\n覚える → すぐ小テスト（再生） 間違える → その場で最小修正 翌日 → もう一回テスト 3日後/7日後 → まとめてテスト 暗記は“作業”ではなく“試験” 暗記はテスト形式が最強。ノートは補助。覚えたかは再生できたかで判定する。\n5) ミス分析（5分類だけで十分）#\rミスはこれだけに分ける。\n知識不足：覚えてない 理解不足：理由や仕組みが弱い 手順ミス：解き方の順序が崩れてる 条件読み違い：問題文の処理が雑 ケアレス：計算/転記/符号/単位 → 対策は「分類ごとの型」で固定できる（次の記事で完成テンプレを出す）。\n6) 1日60分の最小ルーティン（時間がない人用）#\r5分：今日やる問題を決める（“選ぶ”で消耗しない） 40分：問題を解く（解説読みは最低限） 10分：ミス分類＋復習（再発防止だけ） 5分：明日の問題を決める（次の自分を助ける） 7) 最後に：このサイトの使い方#\r左メニューからセクションを選ぶ セクショントップにあるカード目次から記事へ 各記事の最後にチェックがあるので、毎日1つだけでも回す 次に読む → 時間配分の目安（問題中心で伸ばす）\n→ ミスの5分類と対策（完成版）\n→ 毎日60分ルーティン（完成版）\n"},{"id":5,"href":"/docs/05_routine/01_daily60/","title":"毎日ルーティンの作り方（60分/120分/週末）","section":"毎日のルーティン","content":" 毎日ルーティン 時間がない人ほど「毎日の型」で勝つ 伸びる人は、長時間やる日より「崩れない日」を作っている。ルーティンはそのための道具。 結論（ルーティンの核心） 毎日やる内容を固定すると、迷いが減って勉強が続く。\nルーティンは「やる気」を増やすものじゃない。毎日の判断回数を減らして、勉強を回す仕組み。\nまず最初に：このページで言う「ルーティン」の意味#\rこのページのルーティンは、「気合いで頑張る予定表」じゃない。\n毎日、最低限これだけ回せば点が伸びるという 最小構成 のこと。\nルーティンがある → 迷わない → 着手が速い → 続く 続く → ミスが見える → ミスが減る → 点が上がる よくある勘違い 「問題が主役」＝「解くことが目的」ではない。\n問題を解くのは、ミスを見つけるため。ミスが見えない勉強は、点が伸びにくい。\nなぜルーティン化すると強いのか（理屈）#\r受験勉強が崩れる原因は、能力不足よりも毎日の判断コストが多いこと。\n「今日は何やろう…」で時間が溶ける 決めた後も「これでいいのか？」が残って集中が切れる 結果、問題に触れる時間が減る（＝ミスが見えない） ルーティン化はこれを消す。\nやることが固定 → 判断が減る 判断が減る → 着手が速くなる 着手が速い → 毎日続く 続く → ミスが減って点が伸びる ルーティンのゴール 「完璧な計画」じゃない。毎日回る最小構成を作ること。\nまず決めるルール（ここだけは固定）#\r毎日やる時間を固定（15分でもOK。毎日が最優先） 内容は「問題 → ミス → 復習」の順に固定 翌日の問題を前日に決める（迷いゼロ） ここがズレると崩れる 「理解だけの日」が増える（ミスが見えない） 復習が長引いて時間が足りなくなる（原因が曖昧） その日の気分で科目が変わる（積み上がらない） 今日から使える：60分ルーティン（時間がない日の型）#\r5分：今日やる問題を確定（前日に決めていれば0分） 40分：問題（目的：ミス発見） 10分：ミス分類＋復習（再発防止だけ） 5分：明日の問題を決める（次の自分を助ける） 60分ルーティン：守るポイント 「理解だけ」で終わらせない（必ず問題で締める） 復習は10分で切る（長引くなら“原因の言葉”が曖昧） 最後の5分で「明日の問題」を決める（継続の要） 120分ルーティン（標準：伸ばしたい日の型）#\r10分：今日の問題セットを確定（優先順位で選ぶ） 75分：問題（演習：ミスが出る量を確保） 20分：ミス分類＋復習（原因1行＋対策1行＋再テスト1問） 15分：暗記（間違いだけを思い出す） 120分のコツ 伸びる日は「問題の量」より、ミスを潰した数で勝つ。復習を削らない。\n重要：時間の練習は「毎日」じゃなく別枠でやる#\r普段の勉強で優先するのは、再現性（同じ手順で解ける）。\n時間配分の実戦練習は、過去問などでまとめてやる方が効率がいい。\n普段：手順と判断を固定して「ミスの種類」を減らす 別枠（過去問）：時間配分・取捨選択・本番のテンポを練習する 理由 普段から時間に追われると、ミスの原因が見えにくくなる。\nまずはミスの修正で土台を固めて、時間練習は「実戦枠」でまとめてやる。\n週末ルーティン（まとめて整える日）#\r平日を回すほど、週末の“修理”が効く。\n30分：1週間のミスを集計（多い順に並べる） 60分：ミスが多い単元の同類題を解く（弱点を露出させる） 30分：暗記の総テスト（チェックだけ） 15分：来週の「毎日やる範囲」を固定 週末にやると一気に伸びる作業 ミスが多い原因（例：手順ミス）を“手順テンプレ”で統一する 暗記は「全体」じゃなく「間違いだけ」を集中的に 来週の“毎日枠”を固定しておく ルーティンが崩れる典型 → 直し方#\r崩れる原因 毎日やる内容が多すぎる 直し方：60分版に戻して「問題 → ミス → 復習」だけ残す。 崩れる原因 その日の気分で科目が変わる 直し方：前日に“明日やる問題”を決めて固定。 崩れる原因 復習が長引いて疲れる 直し方：原因の言葉をつけ直す。対策は1行、再テスト1問で切る。 崩れる原因 スマホが気になって集中が切れる 直し方：置く/置かないではなく「役割」を固定する（タイマー／記録／必要な解説確認）。通知は切る。 スマホ前提の“最小運用”（机にスマホがあっても成立）#\rスマホがあるとダメ、じゃなくて役割を固定する。\nタイマー（40分/75分） 復習メモ（原因1行＋対策1行） 解説確認（必要なときだけ。だら見禁止） 通知はオフ（ここだけは必須） まとめ スマホは「置く/置かない」じゃなく、使い方を固定する。\n今日のチェック（YESが増えるほど強い）#\rチェック 今日やる問題が決まっている ミスが1つ見つかった（理由まで言える） ミスを1つ潰した（原因1行＋対策1行＋再テスト） 明日の問題が決まっている 次に読む → 全体設計（やること／捨てること）\n→ ミスの5分類と対策\n"},{"id":6,"href":"/docs/02_memory/02_forgetting/","title":"忘却前提の復習設計（いつ復習するか：完成版）","section":"暗記と復習","content":" 完成版 復習は「気分」じゃなく「予定」にする 人は忘れる。忘れるのが普通。だから、忘れる前提で“復習の出番”を先に決める。 結論（これだけ） 復習の強さは「回数」より「タイミング」で決まる。\nいちばん大事なのは 翌日。次が 3日後。その次が 7日後。\nまずは当日＋翌日だけ固定すれば、成績は動く。\nなぜ「翌日」が最重要なのか（理屈）#\r暗記は「入れたら終わり」じゃない。\n時間が経つと、思い出すのに必要な“道”が細くなる。\n翌日は、まだ道が完全に消えていない でも、そのまま放置すると一気に戻れなくなる だから翌日にもう一回“思い出す”と、道が太くなる ここを外すと、復習は「やった気」になりやすい。\n復習の基本形（最短テンプレ）#\r当日：間違いの原因だけ直す（長くやらない） 翌日：同じ形式で再テスト（ここが本番） 3日後：もう一回テスト（“落ちる所”を確定させる） 7日後：まとめテスト（長期に残す） 重要：復習は「読み直し」じゃなく「再テスト」 復習の目的は納得じゃない。次に正解すること。\nだから復習は「もう一回解く／言う」が中心。\nどれくらい復習すればいい？（時間の目安）#\r「復習が長すぎて続かない」が一番もったいない。\n目安はこれでOK。\n当日（最短） 3〜10分 原因ラベル＋1問やり直し。これで十分。 翌日（最重要） 10〜20分 再テスト中心。できない所だけ絞る。 実例：英単語の復習設計（そのまま使える）#\r当日：30語テスト → 間違いだけチェック 翌日：チェック語だけテスト（できたら外す） 3日後：残ったチェックだけテスト 7日後：当日30語をもう一回テスト（抜けの回収） ポイントはこれ：\n全部を何周もしない 間違いだけを追いかける 翌日だけは必ずやる 実例：数学の復習設計（「解き方」が残る形）#\r数学は暗記というより「手順」を残す復習になる。\n当日：ミスの種類を決める（知識/理解/手順/読み/ケアレス） 当日：解き方を“3手”で書く（長文禁止） 翌日：同類題を1問解く（見ずに） 3日後：同類題をもう1問（時間を測る） よくある失敗 → 直し方#\r失敗 復習が「読み直し」になる 直し方：最初に必ず「隠して言う／解く」を入れる。 失敗 復習の予定がなく、気分になる 直し方：翌日だけは固定。カレンダーでも紙でもOK。 失敗 全部を何度もやって時間が溶ける 直し方：「間違いだけ」を回す。正解は捨てる。 失敗 復習が長すぎて続かない 直し方：当日は3分でもOK。翌日の再テストを守る。 今日のチェック（YESなら勝ち） 当日：間違いを1つだけ直して終えた（ダラダラやらない） 翌日の再テストを「いつやるか」決めた 復習は“読み直し”じゃなく“再テスト”になっている 次に読む → 復習の手順（テンプレ：短く強く）\n"},{"id":7,"href":"/docs/01_design/02_time_allocation/","title":"時間配分の目安（問題中心で伸ばす）","section":"勉強の基本設計","content":" 実用 時間配分は「問題の比率」で決まる 理解の時間を削るのではない。問題で判定して、必要分だけ理解を足す。 基本比率（迷ったら固定）#\r平常期：理解 3：問題 7 直前期：理解 1：問題 9 判断基準 問題が解けない理由が「知識不足」なら暗記へ。\n「手順が崩れる」なら解き方を固定。\n「理解不足」なら短い解説→すぐ問題。\n1日の中でのおすすめ配分（例）#\r最初：問題（判定） 次：ミス分類 最後：復習（短く強く） 今日のチェック 問題の時間が一番長い 解説を読み続けず「次の1問」に戻れた "},{"id":8,"href":"/docs/01_design/03_priority/","title":"優先順位：伸びる順番（迷いゼロ）","section":"勉強の基本設計","content":" 原則 やることが多い人ほど「順番」で勝つ 勉強は量より配列。順番が正しいほど、同じ時間で伸びる。 優先順位の固定（これでOK）#\r頻出×取れる ミスが多い 暗記で即伸びる 理解を足す（必要分だけ） コツ 「今日は何しよう…」をゼロにする。前日に次を決めておく。\n"},{"id":9,"href":"/docs/01_design/","title":"勉強の基本設計","section":"オンライン自習室","content":" 全員共通 まずはここだけでいい。伸びる設計の全体像 受験は「本番で解けるか」。そのために、問題→ミス→復習のループを最短化する。 完成版最短で伸ばす“全体設計”今日から迷わない。優先順位・時間配分・手順。 実用時間配分の目安理解と問題の比率／直前期の割合。 原則優先順位：伸びる順番やることが多い人ほど、順番で勝つ。 "},{"id":10,"href":"/docs/02_memory/","title":"暗記と復習","section":"オンライン自習室","content":" 全員共通 暗記は才能じゃない。手順の問題 覚える＝脳に刻む、ではない。思い出す練習を設計する。 完成版暗記は「思い出す」が9割書くよりテスト。再生回数で覚える。 設計忘却前提の復習設計いつ何を復習すればいいか。 "},{"id":11,"href":"/docs/03_review/","title":"復習のやり方","section":"オンライン自習室","content":" 得点化 復習は“短く、強く”。これで点になる 復習の目的は納得じゃない。次に正解する状態を作ること。 完成版復習の手順（テンプレ）何を書き、何を回すかを固定化。 "},{"id":12,"href":"/docs/04_mistakes/","title":"ミス分析と対策","section":"オンライン自習室","content":" 伸びる作業 ミスを潰す人が勝つ ミスは感情じゃなく分類。原因が分かれば対策は固定できる。 完成版ミスの5分類と対策再発防止の型を作る。 "},{"id":13,"href":"/docs/05_routine/","title":"毎日のルーティン","section":"オンライン自習室","content":" 毎日回す 時間がない人ほど“型”で勝つ 毎日同じ判断をしない。ルーティンで脳の負荷をゼロにする。 完成版毎日60分ルーティン最小時間で伸ばす配分。 "}]